mpd_pydb/__init__.py
mpd_pydb/db.py
mpd_pydb/version.py
mpd_pydb-1.0.dist-info/DESCRIPTION.rst
mpd_pydb-1.0.dist-info/METADATA
mpd_pydb-1.0.dist-info/RECORD
mpd_pydb-1.0.dist-info/WHEEL
mpd_pydb-1.0.dist-info/metadata.json
mpd_pydb-1.0.dist-info/top_level.txt
