Metadata-Version: 2.0
Name: mpd-pydb
Version: 1.0
Summary: Module for reading an MPD database
Home-page: ['http://github.com/mineo/mpd_pydb']
Author: Wieland Hoffmann
Author-email: themineo@gmail.com
License: MIT
Download-URL: ['https://github.com/mineo/mpd_pydb/tarball/master']
Platform: UNKNOWN
Classifier: Development Status :: 4 - Beta
Classifier: License :: OSI Approved :: MIT License
Classifier: Natural Language :: English
Classifier: Operating System :: OS Independent
Classifier: Programming Language :: Python :: 2.7
Classifier: Programming Language :: Python :: 3.4
Provides-Extra: docs
Requires-Dist: sphinx; extra == 'docs'
